cos_migrate_tool_for_restore-0.3.22.dist-info/DESCRIPTION.rst
cos_migrate_tool_for_restore-0.3.22.dist-info/METADATA
cos_migrate_tool_for_restore-0.3.22.dist-info/RECORD
cos_migrate_tool_for_restore-0.3.22.dist-info/WHEEL
cos_migrate_tool_for_restore-0.3.22.dist-info/entry_points.txt
cos_migrate_tool_for_restore-0.3.22.dist-info/metadata.json
cos_migrate_tool_for_restore-0.3.22.dist-info/top_level.txt
migrate_tool/__init__.py
migrate_tool/bloomfilter.py
migrate_tool/filter.py
migrate_tool/main.py
migrate_tool/migrator.py
migrate_tool/storage_service.py
migrate_tool/task.py
migrate_tool/worker.py
migrate_tool/services/LocalFileSystem.py
migrate_tool/services/__init__.py
migrate_tool/services/coss3.py
migrate_tool/services/cosv3.py
migrate_tool/services/cosv4.py
migrate_tool/services/oss.py
migrate_tool/services/qiniu.py
migrate_tool/services/s3.py
migrate_tool/services/url_list.py
