Metadata-Version: 2.0
Name: cos-migrate-tool-for-restore
Version: 0.3.22
Summary: migrate tool for object storage services
Home-page: https://www.qcloud.com/
Author: chenxi
Author-email: zuiwanting@gmail.com
License: MIT
Platform: UNKNOWN
Requires-Dist: argparse (==1.4.0)
Requires-Dist: boto (==2.43.0)
Requires-Dist: coscmd (==0.1.8)
Requires-Dist: crcmod (==1.7)
Requires-Dist: leveldb (==0.194)
Requires-Dist: oss2r (==0.0.3)
Requires-Dist: qcloud-cos-v3
Requires-Dist: qcloud-cos-v4
Requires-Dist: qiniu (==7.0.9.1)
Requires-Dist: requests (==2.12.4)
